pybacklogpy/Attachment.py
pybacklogpy/BacklogConfigure.py
pybacklogpy/Category.py
pybacklogpy/CustomField.py
pybacklogpy/GitRepository.py
pybacklogpy/Issue.py
pybacklogpy/Licence.py
pybacklogpy/Notification.py
pybacklogpy/Priority.py
pybacklogpy/Project.py
pybacklogpy/PullRequest.py
pybacklogpy/Resolution.py
pybacklogpy/SharedFile.py
pybacklogpy/Space.py
pybacklogpy/Star.py
pybacklogpy/Status.py
pybacklogpy/Team.py
pybacklogpy/User.py
pybacklogpy/Version.py
pybacklogpy/Watch.py
pybacklogpy/Webhook.py
pybacklogpy/Wiki.py
pybacklogpy/__init__.py
pybacklogpy/const.py
pybacklogpy/modules.py
pybacklogpy-0.12.dist-info/LICENSE
pybacklogpy-0.12.dist-info/METADATA
pybacklogpy-0.12.dist-info/WHEEL
pybacklogpy-0.12.dist-info/top_level.txt
pybacklogpy-0.12.dist-info/RECORD
