Metadata-Version: 2.1
Name: pybacklogpy
Version: 0.12
Summary: A library for backlog api
Home-page: https://kitadakyou.github.io/PyBacklogPy/
Author: Hikaru ETO
Author-email: kitadakyou@gmail.com
License: Apache License 2.0
Platform: UNKNOWN
Classifier: License :: OSI Approved :: Apache Software License
Classifier: Programming Language :: Python :: 3.5
Classifier: Programming Language :: Python :: 3.6
Classifier: Programming Language :: Python :: 3.7
Classifier: Natural Language :: Japanese
Requires-Python: >=3.5
License-File: LICENSE
Requires-Dist: requests (==2.22.0)
